ilthermopy/__init__.py
ilthermopy/compound_list.py
ilthermopy/data_structs.py
ilthermopy/errors.py
ilthermopy/misc.py
ilthermopy/requests.py
ilthermopy/search.py
ilthermopy/updates.py
ilthermopy/data/compounds.csv
ilthermopy-1.1.1.1.dist-info/licenses/LICENSE.md
ilthermopy-1.1.1.1.dist-info/METADATA
ilthermopy-1.1.1.1.dist-info/WHEEL
ilthermopy-1.1.1.1.dist-info/top_level.txt
ilthermopy-1.1.1.1.dist-info/RECORD
