Metadata-Version: 2.4
Name: ilthermopy
Version: 1.1.1.1
Summary: A simple Python wrapper around the ILThermo 2.0 database with SMILES support
Author-email: "Ivan Yu. Chernyshov" <ivan.chernyshoff@gmail.com>
Maintainer-email: "Ivan Yu. Chernyshov" <ivan.chernyshoff@gmail.com>
License: MIT License
Project-URL: documentation, https://ivanchernyshov.github.io/ILThermoPy/
Project-URL: repository, https://github.com/IvanChernyshov/ILThermoPy.git
Project-URL: issues, https://github.com/IvanChernyshov/ILThermoPy/issues
Keywords: ionic liquids,ilthermo,nist,api
Classifier: Development Status :: 5 - Production/Stable
Classifier: License :: OSI Approved :: MIT License
Classifier: Programming Language :: Python :: 3 :: Only
Classifier: Operating System :: OS Independent
Classifier: Intended Audience :: Science/Research
Classifier: Topic :: Scientific/Engineering
Classifier: Topic :: Scientific/Engineering :: Chemistry
Requires-Python: >=3.7
License-File: LICENSE.md
Requires-Dist: importlib-resources>=1.1.0; python_version < "3.9"
Requires-Dist: requests
Requires-Dist: pandas
Dynamic: license-file
